FIR.v
module fir #(
    parameter TAPS = 128,
    parameter FRAC = 15
)(
    input  wire                 clk,
    input  wire                 rst_n,
    input  wire signed [31:0]   feedforward_in,   // input from core
    input  wire signed [31:0]   weight_adjust,    // weight update from core
    input  wire                 go,               // start signal from core
    output reg  signed [31:0]   out_sample,
    output reg                  out_valid,
    output reg                  done              // signals FIR completion to core
);

    reg signed [31:0] w_reg [0:TAPS-1];
    reg signed [31:0] x_reg [0:TAPS-1];

    // MAC pipeline registers
    reg signed [47:0] deltaA;
    reg               deltaA_valid;

    reg signed [47:0] prodB;
    reg               prodB_valid;

    reg signed [63:0] acc;
    reg [7:0] proc_idx;

    reg fir_active;
    integer i;

    always @(posedge clk or negedge rst_n) begin
        if (!rst_n) begin
            for (i = 0; i < TAPS; i=i+1) begin
                w_reg[i] <= 32'sd0;
                x_reg[i] <= 32'sd0;
            end
            deltaA <= 48'sd0; 
            deltaA_valid <= 1'b0; 
            prodB <= 48'sd0; 
            prodB_valid <= 1'b0; 
            acc <= 64'sd0;
            out_sample <= 32'sd0;
            out_valid <= 1'b0;
            done <= 1'b0;
            proc_idx <= 0;
            fir_active <= 1'b0;
        end else begin
            out_valid <= 1'b0;
            done <= 1'b0;

            if (go && !fir_active) begin
                fir_active <= 1'b1;
                acc <= 64'sd0;
                proc_idx <= 0;

                for (i = TAPS-1; i > 0; i=i-1) begin
                    x_reg[i] <= x_reg[i-1];
                end
                x_reg[0] <=  feedforward_in;  
            end

            if (fir_active) begin
                // ---- MAC A: weight update ----
                if (proc_idx < TAPS) begin
                    deltaA <= $signed(weight_adjust) * $signed(x_reg[proc_idx]);
                    deltaA_valid <= 1'b1;
                end else begin
                    deltaA <= 48'sd0;
                    deltaA_valid <= 1'b0;
                end

                if (deltaA_valid && proc_idx != 0) begin
                    w_reg[proc_idx-1] <= w_reg[proc_idx-1] + ($signed(deltaA) >>> FRAC);
                end

                // ---- MAC B: output computation ----
                if (proc_idx-1 != 0 && deltaA_valid) begin
                    prodB <= $signed(w_reg[proc_idx-2]) * $signed(x_reg[proc_idx-2]);
                    prodB_valid <= 1'b1;
                end else begin
                    prodB <= 48'sd0;
                    prodB_valid <= 1'b0;
                end


                if (prodB_valid) begin
                    acc <= acc + ($signed(prodB) >>> FRAC);
                end

                // increment index
                proc_idx <= proc_idx + 1'b1;

                // FIR done
                if (proc_idx == TAPS + 2) begin
                    out_sample <= acc[31:0];
                    out_valid <= 1'b1;
                    done <= 1'b1;       // notify core
                    fir_active <= 1'b0; // reset for next run
                    acc <= 64'sd0;
                    proc_idx <= 0;
                end
            end
        end
    end

endmodule

core.v
module core #(
    parameter FRAC = 15
)(
    input  wire         clk,
    input  wire         rst_n,
    input  wire         in_valid,          // from input_buffer
    input  wire signed [15:0] error_in,
    input  wire signed [15:0] feedforward_in,
    input  wire signed [15:0] desired_in,
    input  wire signed [15:0] u_in,        // step-size

    input  wire         fir_done,          // FIR done signal
    input  wire signed [31:0] fir_out,     // FIR output

    output reg signed [31:0] feedforward_out, // feed to FIR
    output reg signed [31:0] weight_adjust,   // (error - desired) * u
    output reg signed [31:0] out_sample,      // core output from FIR
    output reg               out_valid,       // core output ready
    output reg               fir_go           // go signal for FIR
);

    localparam S_IDLE = 2'd0, S_RUN = 2'd1, S_DONE = 2'd2;
    reg [1:0] state;

    always @(posedge clk or negedge rst_n) begin
        if (!rst_n) begin
            state <= S_IDLE;
            feedforward_out <= 32'sd0;
            weight_adjust <= 32'sd0;
            out_sample <= 32'sd0;
            out_valid <= 1'b0;
            fir_go <= 1'b0;
        end else begin
            out_valid <= 1'b0; // default
            fir_go <= 1'b0;    // default

            case (state)
                S_IDLE: begin
                    if (in_valid) begin
                        // compute weight adjustment
                        weight_adjust <= ($signed(error_in) - $signed(desired_in)) * $signed(u_in);
                        feedforward_out <= feedforward_in;  // feed input to FIR
                        fir_go <= 1'b1;                     // signal FIR to start
                        state <= S_RUN;
                    end
                end

                S_RUN: begin
                    // wait for FIR to finish
                    if (fir_done) begin
                        // capture FIR output
                        out_sample <= fir_out;
                        out_valid <= 1'b1;  // core output ready
                        state <= S_DONE;
                    end
                end

                S_DONE: begin
                    state <= S_IDLE; // ready for next input
                end
            endcase
        end
    end

endmodule

input_buffer.v
module input_buffer (
    input  wire         clk,
    input  wire         rst_n,
    input  wire         in_valid,
    input  wire signed [15:0] error_in,
    input  wire signed [15:0] feedforward_in,
    input  wire signed [15:0] desired_in,
    input  wire signed [15:0] u_in,

    output reg  signed [15:0] error_out,
    output reg  signed [15:0] feedforward_out,
    output reg  signed [15:0] desired_out,
    output reg  signed [15:0] u_out,
    output reg                outvalid
);

    always @(posedge clk or negedge rst_n) begin
        if (!rst_n) begin

            error_out       <= 16'sd0;
            feedforward_out <= 16'sd0;
            desired_out     <= 16'sd0;
            u_out           <= 16'sd0;
            outvalid        <= 1'b0;
        end else if (in_valid) begin
            error_out       <= error_in;
            feedforward_out <= feedforward_in;
            desired_out     <= desired_in;
            u_out           <= u_in;
            outvalid        <= 1'b1;
        end else begin
            outvalid <= 1'b0;
        end
    end

endmodule

lms_top.v
module lms_top (
    input  wire         clk,
    input  wire         rst_n,
    input  wire         in_valid,           // new input sample valid
    input  wire signed [15:0] error_in,     // LMS error
    input  wire signed [15:0] feedforward_in, // optional feedback or initial feedforward
    input  wire signed [15:0] desired_in,   // desired output
    input  wire signed [15:0] u_in,         // LMS step size
    output wire signed [31:0] out_sample,   // LMS filter output
    output wire                out_valid     // output valid signal
);

    parameter TAPS = 128;

    // ------------------------
    // Internal wires
    // ------------------------
    wire signed [31:0] feedforward_core;
    wire signed [31:0] weight_adjust_core;
    wire                core_out_valid;
    wire                fir_go;
    wire                fir_done;

    wire signed [15:0] error_buf;
    wire signed [15:0] feedforward_buf;
    wire signed [15:0] desired_buf;
    wire signed [15:0] u_buf;
    wire                buf_valid;

    // ------------------------
    // Input Buffer
    // ------------------------
    input_buffer ibuf (
        .clk(clk),
        .rst_n(rst_n),
        .in_valid(in_valid),
        .error_in(error_in),
        .feedforward_in(feedforward_in),
        .desired_in(desired_in),
        .u_in(u_in),
        .error_out(error_buf),
        .feedforward_out(feedforward_buf),
        .desired_out(desired_buf),
        .u_out(u_buf),
        .outvalid(buf_valid)
    );

    // ------------------------
    // Core FSM + MAC
    // ------------------------
    core core_inst (
        .clk(clk),
        .rst_n(rst_n),
        .in_valid(buf_valid),              // use buffered valid
        .error_in(error_buf),
        .feedforward_in(feedforward_buf),
        .desired_in(desired_buf),
        .u_in(u_buf),
        .fir_done(fir_done),               // FIR handshake
        .feedforward_out(feedforward_core),
        .weight_adjust(weight_adjust_core),
        .out_sample(out_sample),                     // optional: core could output FIR capture if desired
        .out_valid(core_out_valid),
        .fir_go(fir_go)                    // signal FIR to start
    );

    // ------------------------
    // Dual-MAC FIR + Weight Module
    // ------------------------
    fir #(
        .TAPS(TAPS)
    ) fir_inst (
        .clk(clk),
        .rst_n(rst_n),
        .feedforward_in(feedforward_core),
        .weight_adjust(weight_adjust_core),
        .go(fir_go),
        .out_sample(out_sample),
        .out_valid(out_valid),
        .done(fir_done)
    );

endmodule

tb_lms_128.v
`timescale 1ns/1ps

module tb_lms_top;

    reg clk;
    reg valid;
    reg rst_n;
    reg signed [15:0] error_in;
    reg signed [15:0] feedforward_in;
    reg signed [15:0] desired_in;
    reg signed [15:0] u_in;

    wire signed [31:0] out_sample;
    wire out_valid;

    parameter CLK_PERIOD = 10;

    // Clock generation
    initial clk = 0;
    always #(CLK_PERIOD/2) clk = ~clk;

    // Instantiate LMS top module
    lms_top dut (
        .clk(clk),
        .rst_n(rst_n),
        .in_valid(valid),
        .error_in(error_in),
        .feedforward_in(feedforward_in),
        .desired_in(desired_in),
        .u_in(u_in),
        .out_sample(out_sample),
        .out_valid(out_valid)
    );

    // Testbench stimulus
    integer i;
    reg [7:0] cycle_count;

    initial begin
        rst_n = 0;
        error_in = 0;
        feedforward_in = 0;
        desired_in = 0;
        u_in = 16'sd16384; // example step size in Q1.15
        cycle_count = 0;

        #50;
        rst_n = 1;

        // Run simulation for a while
        for (i = 0; i < 20000; i = i + 1) begin
            cycle_count = cycle_count + 1;

            if (cycle_count == 200) begin
                // Feed a new input every 200 cycles
                error_in = $random % 100 - 50;
                valid=1;
                feedforward_in = $random % 100 - 50;
                desired_in = $random % 100 - 50;
                cycle_count = 0; // reset counter
            end else begin
                error_in = 0;
                valid=0;
                feedforward_in = 0;
                desired_in = 0;
            end

            @(posedge clk);
        end

        $stop;
    end

    // Optional: monitor outputs
    initial begin
        $dumpfile("lms_tb.vcd");
        $dumpvars(0, tb_lms_top);
    end

    always @(posedge clk) begin
        if (out_valid) begin
            $display("Time %0t: out_sample = %d", $time, out_sample);
        end
    end

endmodule

lms_tb.vcd
$date
	Wed Nov 05 20:55:02 2025
$end
$version
	Icarus Verilog
$end
$timescale
	1ps
$end
$scope module tb_lms_top $end
$var wire 32 ! out_sample [31:0] $end
$var wire 1 " out_valid $end
$var parameter 32 # CLK_PERIOD $end
$var reg 1 $ clk $end
$var reg 8 % cycle_count [7:0] $end
$var reg 16 & desired_in [15:0] $end
$var reg 16 ' error_in [15:0] $end
$var reg 16 ( feedforward_in [15:0] $end
$var reg 1 ) rst_n $end
$var reg 16 * u_in [15:0] $end
$var reg 1 + valid $end
$var integer 32 , i [31:0] $end
$scope module dut $end
$var wire 1 $ clk $end
$var wire 16 - desired_in [15:0] $end
$var wire 16 . error_in [15:0] $end
$var wire 16 / feedforward_in [15:0] $end
$var wire 1 + in_valid $end
$var wire 32 0 out_sample [31:0] $end
$var wire 1 ) rst_n $end
$var wire 16 1 u_in [15:0] $end
$var wire 32 2 weight_adjust_core [31:0] $end
$var wire 16 3 u_buf [15:0] $end
$var wire 1 " out_valid $end
$var wire 1 4 fir_go $end
$var wire 1 5 fir_done $end
$var wire 32 6 feedforward_core [31:0] $end
$var wire 16 7 feedforward_buf [15:0] $end
$var wire 16 8 error_buf [15:0] $end
$var wire 16 9 desired_buf [15:0] $end
$var wire 1 : core_out_valid $end
$var wire 1 ; buf_valid $end
$var parameter 32 < TAPS $end
$scope module core_inst $end
$var wire 1 $ clk $end
$var wire 32 = fir_out [31:0] $end
$var wire 1 ) rst_n $end
$var wire 16 > u_in [15:0] $end
$var wire 1 ; in_valid $end
$var wire 1 5 fir_done $end
$var wire 16 ? feedforward_in [15:0] $end
$var wire 16 @ error_in [15:0] $end
$var wire 16 A desired_in [15:0] $end
$var parameter 32 B FRAC $end
$var parameter 2 C S_DONE $end
$var parameter 2 D S_IDLE $end
$var parameter 2 E S_RUN $end
$var reg 32 F feedforward_out [31:0] $end
$var reg 1 4 fir_go $end
$var reg 32 G out_sample [31:0] $end
$var reg 1 : out_valid $end
$var reg 2 H state [1:0] $end
$var reg 32 I weight_adjust [31:0] $end
$upscope $end
$scope module fir_inst $end
$var wire 1 $ clk $end
$var wire 32 J feedforward_in [31:0] $end
$var wire 1 4 go $end
$var wire 1 ) rst_n $end
$var wire 32 K weight_adjust [31:0] $end
$var parameter 32 L FRAC $end
$var parameter 32 M TAPS $end
$var reg 64 N acc [63:0] $end
$var reg 48 O deltaA [47:0] $end
$var reg 1 P deltaA_valid $end
$var reg 1 5 done $end
$var reg 1 Q fir_active $end
$var reg 32 R out_sample [31:0] $end
$var reg 1 " out_valid $end
$var reg 8 S proc_idx [7:0] $end
$var reg 48 T prodB [47:0] $end
$var reg 1 U prodB_valid $end
$var integer 32 V i [31:0] $end
$upscope $end
$scope module ibuf $end
$var wire 1 $ clk $end
$var wire 16 W desired_in [15:0] $end
$var wire 16 X error_in [15:0] $end
$var wire 16 Y feedforward_in [15:0] $end
$var wire 1 + in_valid $end
$var wire 1 ) rst_n $end
$var wire 16 Z u_in [15:0] $end
$var reg 16 [ desired_out [15:0] $end
$var reg 16 \ error_out [15:0] $end
$var reg 16 ] feedforward_out [15:0] $end
$var reg 1 ; outvalid $end
$var reg 16 ^ u_out [15:0] $end
$upscope $end
$upscope $end
$upscope $end
$enddefinitions $end
$comment Show the parameter values. $end
$dumpall
b10000000 M
b1111 L
b1 E
b0 D
b10 C
b1111 B
b10000000 <
b1010 #
$end
#0
$dumpvars
b0 ^
b0 ]
b0 \
b0 [
b100000000000000 Z
b0 Y
b0 X
b0 W
b10000000 V
0U
b0 T
b0 S
b0 R
0Q
0P
b0 O
b0 N
b0 K
b0 J
b0 I
b0 H
b0 G
b0 F
b0 A
b0 @
b0 ?
b0 >
bz =
0;
0:
b0 9
b0 8
b0 7
b0 6
05
04
b0 3
b0 2
b100000000000000 1
b0 0
b0 /
b0 .
b0 -
bx ,
x+
b100000000000000 *
0)
b0 (
b0 '
b0 &
b0 %
0$
0"
b0 !
$end
#5000
b10000000 V
1$
#10000
0$
#15000
b10000000 V
1$
#20000
0$
#25000
b10000000 V
1$
#30000
0$
#35000
b10000000 V
1$
#40000
0$
#45000
b10000000 V
1$
#50000
0$
0+
b1 %
b0 ,
1)
#55000
b10 %
b1 ,
1$
#60000
0$
#65000
b11 %
b10 ,
1$
#70000
0$
#75000
b100 %
b11 ,
1$
#80000
0$
#85000
b101 %
b100 ,
1$
#90000
0$
#95000
b110 %
b101 ,
1$
#100000
0$
#105000
b111 %
b110 ,
1$
#110000
0$
#115000
b1000 %
b111 ,
1$
#120000
0$
#125000
b1001 %
b1000 ,
1$
#130000
0$
#135000
b1010 %
b1001 ,
1$
#140000
0$
#145000
b1011 %
b1010 ,
1$
#150000
0$
#155000
b1100 %
b1011 ,
1$
#160000
0$
#165000
b1101 %
b1100 ,
1$
#170000
0$
#175000
b1110 %
b1101 ,
1$
#180000
0$
#185000
b1111 %
b1110 ,
1$
#190000
0$
#195000
b10000 %
b1111 ,
1$
#200000
0$
#205000
b10001 %
b10000 ,
1$
#210000
0$
#215000
b10010 %
b10001 ,
1$
#220000
0$
#225000
b10011 %
b10010 ,
1$
#230000
0$
#235000
b10100 %
b10011 ,
1$
#240000
0$
#245000
b10101 %
b10100 ,
1$
#250000
0$
#255000
b10110 %
b10101 ,
1$
#260000
0$
#265000
b10111 %
b10110 ,
1$
#270000
0$
#275000
b11000 %
b10111 ,
1$
#280000
0$
#285000
b11001 %
b11000 ,
1$
#290000
0$
#295000
b11010 %
b11001 ,
1$
#300000
0$
#305000
b11011 %
b11010 ,
1$
#310000
0$
#315000
b11100 %
b11011 ,
1$
#320000
0$
#325000
b11101 %
b11100 ,
1$
#330000
0$
#335000
b11110 %
b11101 ,
1$
#340000
0$
#345000
b11111 %
b11110 ,
1$
#350000
0$
#355000
b100000 %
b11111 ,
1$
#360000
0$
#365000
b100001 %
b100000 ,
1$
#370000
0$
#375000
b100010 %
b100001 ,
1$
#380000
0$
#385000
b100011 %
b100010 ,
1$
#390000
0$
#395000
b100100 %
b100011 ,
1$
#400000
0$
#405000
b100101 %
b100100 ,
1$
#410000
0$
#415000
b100110 %
b100101 ,
1$
#420000
0$
#425000
b100111 %
b100110 ,
1$
#430000
0$
#435000
b101000 %
b100111 ,
1$
#440000
0$
#445000
b101001 %
b101000 ,
1$
#450000
0$
#455000
b101010 %
b101001 ,
1$
#460000
0$
#465000
b101011 %
b101010 ,
1$
#470000
0$
#475000
b101100 %
b101011 ,
1$
#480000
0$
#485000
b101101 %
b101100 ,
1$
#490000
0$
#495000
b101110 %
b101101 ,
1$
#500000
0$
#505000
b101111 %
b101110 ,
1$
#510000
0$
#515000
b110000 %
b101111 ,
1$
#520000
0$
#525000
b110001 %
b110000 ,
1$
#530000
0$
#535000
b110010 %
b110001 ,
1$
#540000
0$
#545000
b110011 %
b110010 ,
1$
#550000
0$
#555000
b110100 %
b110011 ,
1$
#560000
0$
#565000
b110101 %
b110100 ,
1$
#570000
0$
#575000
b110110 %
b110101 ,
1$
#580000
0$
#585000
b110111 %
b110110 ,
1$
#590000
0$
#595000
b111000 %
b110111 ,
1$
#600000
0$
#605000
b111001 %
b111000 ,
1$
#610000
0$
#615000
b111010 %
b111001 ,
1$
#620000
0$
#625000
b111011 %
b111010 ,
1$
#630000
0$
#635000
b111100 %
b111011 ,
1$
#640000
0$
#645000
b111101 %
b111100 ,
1$
#650000
0$
#655000
b111110 %
b111101 ,
1$
#660000
0$
#665000
b111111 %
b111110 ,
1$
#670000
0$
#675000
b1000000 %
b111111 ,
1$
#680000
0$
#685000
b1000001 %
b1000000 ,
1$
#690000
0$
#695000
b1000010 %
b1000001 ,
1$
#700000
0$
#705000
b1000011 %
b1000010 ,
1$
#710000
0$
#715000
b1000100 %
b1000011 ,
1$
#720000
0$
#725000
b1000101 %
b1000100 ,
1$
#730000
0$
#735000
b1000110 %
b1000101 ,
1$
#740000
0$
#745000
b1000111 %
b1000110 ,
1$
#750000
0$
#755000
b1001000 %
b1000111 ,
1$
#760000
0$
#765000
b1001001 %
b1001000 ,
1$
#770000
0$
#775000
b1001010 %
b1001001 ,
1$
#780000
0$
#785000
b1001011 %
b1001010 ,
1$
#790000
0$
#795000
b1001100 %
b1001011 ,
1$
#800000
0$
#805000
b1001101 %
b1001100 ,
1$
#810000
0$
#815000
b1001110 %
b1001101 ,
1$
#820000
0$
#825000
b1001111 %
b1001110 ,
1$
#830000
0$
#835000
b1010000 %
b1001111 ,
1$
#840000
0$
#845000
b1010001 %
b1010000 ,
1$
#850000
0$
#855000
b1010010 %
b1010001 ,
1$
#860000
0$
#865000
b1010011 %
b1010010 ,
1$
#870000
0$
#875000
b1010100 %
b1010011 ,
1$
#880000
0$
#885000
b1010101 %
b1010100 ,
1$
#890000
0$
#895000
b1010110 %
b1010101 ,
1$
#900000
0$
#905000
b1010111 %
b1010110 ,
1$
#910000
0$
#915000
b1011000 %
b1010111 ,
1$
#920000
0$
#925000
b1011001 %
b1011000 ,
1$
#930000
0$
#935000
b1011010 %
b1011001 ,
1$
#940000
0$
#945000
b1011011 %
b1011010 ,
1$
#950000
0$
#955000
b1011100 %
b1011011 ,
1$
#960000
0$
#965000
b1011101 %
b1011100 ,
1$
#970000
0$
#975000
b1011110 %
b1011101 ,
1$
#980000
0$
#985000
b1011111 %
b1011110 ,
1$
#990000
0$
#995000
b1100000 %
b1011111 ,
1$
#1000000
0$
#1005000
b1100001 %
b1100000 ,
1$
#1010000
0$
#1015000
b1100010 %
b1100001 ,
1$
#1020000
0$
#1025000
b1100011 %
b1100010 ,
1$
#1030000
0$
#1035000
b1100100 %
b1100011 ,
1$
#1040000
0$
#1045000
b1100101 %
b1100100 ,
1$
#1050000
0$
#1055000
b1100110 %
b1100101 ,
1$
#1060000
0$
#1065000
b1100111 %
b1100110 ,
1$
#1070000
0$
#1075000
b1101000 %
b1100111 ,
1$
#1080000
0$
#1085000
b1101001 %
b1101000 ,
1$
#1090000
0$
#1095000
b1101010 %
b1101001 ,
1$
#1100000
0$
#1105000
b1101011 %
b1101010 ,
1$
#1110000
0$
#1115000
b1101100 %
b1101011 ,
1$
#1120000
0$
#1125000
b1101101 %
b1101100 ,
1$
#1130000
0$
#1135000
b1101110 %
b1101101 ,
1$
#1140000
0$
#1145000
b1101111 %
b1101110 ,
1$
#1150000
0$
#1155000
b1110000 %
b1101111 ,
1$
#1160000
0$
#1165000
b1110001 %
b1110000 ,
1$
#1170000
0$
#1175000
b1110010 %
b1110001 ,
1$
#1180000
0$
#1185000
b1110011 %
b1110010 ,
1$
#1190000
0$
#1195000
b1110100 %
b1110011 ,
1$
#1200000
0$
#1205000
b1110101 %
b1110100 ,
1$
#1210000
0$
#1215000
b1110110 %
b1110101 ,
1$
#1220000
0$
#1225000
b1110111 %
b1110110 ,
1$
#1230000
0$
#1235000
b1111000 %
b1110111 ,
1$
#1240000
0$
#1245000
b1111001 %
b1111000 ,
1$
#1250000
0$
#1255000
b1111010 %
b1111001 ,
1$
#1260000
0$
#1265000
b1111011 %
b1111010 ,
1$
#1270000
0$
#1275000
b1111100 %
b1111011 ,
1$
#1280000
0$
#1285000
b1111101 %
b1111100 ,
1$
#1290000
0$
#1295000
b1111110 %
b1111101 ,
1$
#1300000
0$
#1305000
b1111111 %
b1111110 ,
1$
#1310000
0$
#1315000
b10000000 %
b1111111 ,
1$
#1320000
0$
#1325000
b10000001 %
b10000000 ,
1$
#1330000
0$
#1335000
b10000010 %
b10000001 ,
1$
#1340000
0$
#1345000
b10000011 %
b10000010 ,
1$
#1350000
0$
#1355000
b10000100 %
b10000011 ,
1$
#1360000
0$
#1365000
b10000101 %
b10000100 ,
1$
#1370000
0$
#1375000
b10000110 %
b10000101 ,
1$
#1380000
0$
#1385000
b10000111 %
b10000110 ,
1$
#1390000
0$
#1395000
b10001000 %
b10000111 ,
1$
#1400000
0$
#1405000
b10001001 %
b10001000 ,
1$
#1410000
0$
#1415000
b10001010 %
b10001001 ,
1$
#1420000
0$
#1425000
b10001011 %
b10001010 ,
1$
#1430000
0$
#1435000
b10001100 %
b10001011 ,
1$
#1440000
0$
#1445000
b10001101 %
b10001100 ,
1$
#1450000
0$
#1455000
b10001110 %
b10001101 ,
1$
#1460000
0$
#1465000
b10001111 %
b10001110 ,
1$
#1470000
0$
#1475000
b10010000 %
b10001111 ,
1$
#1480000
0$
#1485000
b10010001 %
b10010000 ,
1$
#1490000
0$
#1495000
b10010010 %
b10010001 ,
1$
#1500000
0$
#1505000
b10010011 %
b10010010 ,
1$
#1510000
0$
#1515000
b10010100 %
b10010011 ,
1$
#1520000
0$
#1525000
b10010101 %
b10010100 ,
1$
#1530000
0$
#1535000
b10010110 %
b10010101 ,
1$
#1540000
0$
#1545000
b10010111 %
b10010110 ,
1$
#1550000
0$
#1555000
b10011000 %
b10010111 ,
1$
#1560000
0$
#1565000
b10011001 %
b10011000 ,
1$
#1570000
0$
#1575000
b10011010 %
b10011001 ,
1$
#1580000
0$
#1585000
b10011011 %
b10011010 ,
1$
#1590000
0$
#1595000
b10011100 %
b10011011 ,
1$
#1600000
0$
#1605000
b10011101 %
b10011100 ,
1$
#1610000
0$
#1615000
b10011110 %
b10011101 ,
1$
#1620000
0$
#1625000
b10011111 %
b10011110 ,
1$
#1630000
0$
#1635000
b10100000 %
b10011111 ,
1$
#1640000
0$
#1645000
b10100001 %
b10100000 ,
1$
#1650000
0$
#1655000
b10100010 %
b10100001 ,
1$
#1660000
0$
#1665000
b10100011 %
b10100010 ,
1$
#1670000
0$
#1675000
b10100100 %
b10100011 ,
1$
#1680000
0$
#1685000
b10100101 %
b10100100 ,
1$
#1690000
0$
#1695000
b10100110 %
b10100101 ,
1$
#1700000
0$
#1705000
b10100111 %
b10100110 ,
1$
#1710000
0$
#1715000
b10101000 %
b10100111 ,
1$
#1720000
0$
#1725000
b10101001 %
b10101000 ,
1$
#1730000
0$
#1735000
b10101010 %
b10101001 ,
1$
#1740000
0$
#1745000
b10101011 %
b10101010 ,
1$
#1750000
0$
#1755000
b10101100 %
b10101011 ,
1$
#1760000
0$
#1765000
b10101101 %
b10101100 ,
1$
#1770000
0$
#1775000
b10101110 %
b10101101 ,
1$
#1780000
0$
#1785000
b10101111 %
b10101110 ,
1$
#1790000
0$
#1795000
b10110000 %
b10101111 ,
1$
#1800000
0$
#1805000
b10110001 %
b10110000 ,
1$
#1810000
0$
#1815000
b10110010 %
b10110001 ,
1$
#1820000
0$
#1825000
b10110011 %
b10110010 ,
1$
#1830000
0$
#1835000
b10110100 %
b10110011 ,
1$
#1840000
0$
#1845000
b10110101 %
b10110100 ,
1$
#1850000
0$
#1855000
b10110110 %
b10110101 ,
1$
#1860000
0$
#1865000
b10110111 %
b10110110 ,
1$
#1870000
0$
#1875000
b10111000 %
b10110111 ,
1$
#1880000
0$
#1885000
b10111001 %
b10111000 ,
1$
#1890000
0$
#1895000
b10111010 %
b10111001 ,
1$
#1900000
0$
#1905000
b10111011 %
b10111010 ,
1$
#1910000
0$
#1915000
b10111100 %
b10111011 ,
1$
#1920000
0$
#1925000
b10111101 %
b10111100 ,
1$
#1930000
0$
#1935000
b10111110 %
b10111101 ,
1$
#1940000
0$
#1945000
b10111111 %
b10111110 ,
1$
#1950000
0$
#1955000
b11000000 %
b10111111 ,
1$
#1960000
0$
#1965000
b11000001 %
b11000000 ,
1$
#1970000
0$
#1975000
b11000010 %
b11000001 ,
1$
#1980000
0$
#1985000
b11000011 %
b11000010 ,
1$
#1990000
0$
#1995000
b11000100 %
b11000011 ,
1$
#2000000
0$
#2005000
b11000101 %
b11000100 ,
1$
#2010000
0$
#2015000
b11000110 %
b11000101 ,
1$
#2020000
0$
#2025000
b11000111 %
b11000110 ,
1$
#2030000
0$
#2035000
1;
b100000000000000 3
b100000000000000 >
b100000000000000 ^
b1111111110100111 9
b1111111110100111 A
b1111111110100111 [
b1111111101101011 7
b1111111101101011 ?
b1111111101101011 ]
b1111111111111110 8
b1111111111111110 @
b1111111111111110 \
b1111111110100111 &
b1111111110100111 -
b1111111110100111 W
b1111111101101011 (
b1111111101101011 /
b1111111101101011 Y
1+
b1111111111111110 '
b1111111111111110 .
b1111111111111110 X
b0 %
b11000111 ,
1$
#2040000
0$
#2045000
b1 H
14
b11111111111111111111111101101011 6
b11111111111111111111111101101011 F
b11111111111111111111111101101011 J
b101011100000000000000 2
b101011100000000000000 I
b101011100000000000000 K
0;
b0 &
b0 -
b0 W
b0 (
b0 /
b0 Y
0+
b0 '
b0 .
b0 X
b1 %
b11001000 ,
1$
#2050000
0$
#2055000
04
1Q
b0 V
b10 %
b11001001 ,
1$
#2060000
0$
#2065000
b1 S
1P
b111111111111111111110011010101110100000000000000 O
b11 %
b11001010 ,
1$
#2070000
0$
#2075000
b10 S
b0 O
b100 %
b11001011 ,
1$
#2080000
0$
#2085000
b11 S
1U
b11101011110010111010 T
b101 %
b11001100 ,
1$
#2090000
0$
#2095000
b100 S
b11101 N
b0 T
b110 %
b11001101 ,
1$
#2100000
0$
#2105000
b101 S
b111 %
b11001110 ,
1$
#2110000
0$
#2115000
b110 S
b1000 %
b11001111 ,
1$
#2120000
0$
#2125000
b111 S
b1001 %
b11010000 ,
1$
#2130000
0$
#2135000
b1000 S
b1010 %
b11010001 ,
1$
#2140000
0$
#2145000
b1001 S
b1011 %
b11010010 ,
1$
#2150000
0$
#2155000
b1010 S
b1100 %
b11010011 ,
1$
#2160000
0$
#2165000
b1011 S
b1101 %
b11010100 ,
1$
#2170000
0$
#2175000
b1100 S
b1110 %
b11010101 ,
1$
#2180000
0$
#2185000
b1101 S
b1111 %
b11010110 ,
1$
#2190000
0$
#2195000
b1110 S
b10000 %
b11010111 ,
1$
#2200000
0$
#2205000
b1111 S
b10001 %
b11011000 ,
1$
#2210000
0$
#2215000
b10000 S
b10010 %
b11011001 ,
1$
#2220000
0$
#2225000
b10001 S
b10011 %
b11011010 ,
1$
#2230000
0$
#2235000
b10010 S
b10100 %
b11011011 ,
1$
#2240000
0$
#2245000
b10011 S
b10101 %
b11011100 ,
1$
#2250000
0$
#2255000
b10100 S
b10110 %
b11011101 ,
1$
#2260000
0$
#2265000
b10101 S
b10111 %
b11011110 ,
1$
#2270000
0$
#2275000
b10110 S
b11000 %
b11011111 ,
1$
#2280000
0$
#2285000
b10111 S
b11001 %
b11100000 ,
1$
#2290000
0$
#2295000
b11000 S
b11010 %
b11100001 ,
1$
#2300000
0$
#2305000
b11001 S
b11011 %
b11100010 ,
1$
#2310000
0$
#2315000
b11010 S
b11100 %
b11100011 ,
1$
#2320000
0$
#2325000
b11011 S
b11101 %
b11100100 ,
1$
#2330000
0$
#2335000
b11100 S
b11110 %
b11100101 ,
1$
#2340000
0$
#2345000
b11101 S
b11111 %
b11100110 ,
1$
#2350000
0$
#2355000
b11110 S
b100000 %
b11100111 ,
1$
#2360000
0$
#2365000
b11111 S
b100001 %
b11101000 ,
1$
#2370000
0$
#2375000
b100000 S
b100010 %
b11101001 ,
1$
#2380000
0$
#2385000
b100001 S
b100011 %
b11101010 ,
1$
#2390000
0$
#2395000
b100010 S
b100100 %
b11101011 ,
1$
#2400000
0$
#2405000
b100011 S
b100101 %
b11101100 ,
1$
#2410000
0$
#2415000
b100100 S
b100110 %
b11101101 ,
1$
#2420000
0$
#2425000
b100101 S
b100111 %
b11101110 ,
1$
#2430000
0$
#2435000
b100110 S
b101000 %
b11101111 ,
1$
#2440000
0$
#2445000
b100111 S
b101001 %
b11110000 ,
1$
#2450000
0$
#2455000
b101000 S
b101010 %
b11110001 ,
1$
#2460000
0$
#2465000
b101001 S
b101011 %
b11110010 ,
1$
#2470000
0$
#2475000
b101010 S
b101100 %
b11110011 ,
1$
#2480000
0$
#2485000
b101011 S
b101101 %
b11110100 ,
1$
#2490000
0$
#2495000
b101100 S
b101110 %
b11110101 ,
1$
#2500000
0$
#2505000
b101101 S
b101111 %
b11110110 ,
1$
#2510000
0$
#2515000
b101110 S
b110000 %
b11110111 ,
1$
#2520000
0$
#2525000
b101111 S
b110001 %
b11111000 ,
1$
#2530000
0$
#2535000
b110000 S
b110010 %
b11111001 ,
1$
#2540000
0$
#2545000
b110001 S
b110011 %
b11111010 ,
1$
#2550000
0$
#2555000
b110010 S
b110100 %
b11111011 ,
1$
#2560000
0$
#2565000
b110011 S
b110101 %
b11111100 ,
1$
#2570000
0$
#2575000
b110100 S
b110110 %
b11111101 ,
1$
#2580000
0$
#2585000
b110101 S
b110111 %
b11111110 ,
1$
#2590000
0$
#2595000
b110110 S
b111000 %
b11111111 ,
1$
#2600000
0$
#2605000
b110111 S
b111001 %
b100000000 ,
1$
#2610000
0$
#2615000
b111000 S
b111010 %
b100000001 ,
1$
#2620000
0$
#2625000
b111001 S
b111011 %
b100000010 ,
1$
#2630000
0$
#2635000
b111010 S
b111100 %
b100000011 ,
1$
#2640000
0$
#2645000
b111011 S
b111101 %
b100000100 ,
1$
#2650000
0$
#2655000
b111100 S
b111110 %
b100000101 ,
1$
